{"is_source_file": false, "format": "", "description": "", "external_files": [], "external_methods": [], "published": [], "classes": [], "methods": [], "calls": [], "search-terms": [], "state": 2, "file_id": 12, "knowledge_revision": 19, "git_revision": "64dec735c1be022737d334a6ff795075141cc17c", "hash": "fabb6a5b7f2c03fade1c2d505d186e56", "format-version": 4, "code-base-name": "snake_game_frontend", "filename": "README.md", "revision_history": [{"19": "64dec735c1be022737d334a6ff795075141cc17c"}]}